[
  {
    "name": "BleepingComputer",
    "url": "https://www.bleepingcomputer.com/feed/",
    "vendor": "News"
  },
  {
    "name": "Krebs on Security",
    "url": "https://krebsonsecurity.com/feed/",
    "vendor": "News"
  },
  {
    "name": "CISA Advisories",
    "url": "https://www.cisa.gov/cybersecurity-advisories.xml",
    "vendor": "Government"
  },
  {
    "name": "Palo Alto Networks",
    "url": "https://security.paloaltonetworks.com/rss.xml",
    "vendor": "Palo Alto"
  },
  {
    "name": "Cisco Advisories",
    "url": "https://sec.cloudapps.cisco.com/security/center/psirtrss20/CiscoSecurityAdvisory.xml",
    "vendor": "Cisco"
  },
  {
    "name": "Ivanti Security",
    "url": "https://www.ivanti.com/blog/topics/security-advisory/rss",
    "vendor": "Ivanti"
  }
]